[
  {
    "plate": "31477902",
    "mfg": "מ.ג סין",
    "model": "EHS PHEV",
    "year": 2022.0,
    "trim": "NET-UP",
    "country": "IL",
    "price_at_reg": 168888.0,
    "km": 49850.0,
    "age": 3.89,
    "ownership": "פרטי",
    "hand": 2.0,
    "hand_history": "פרטי (08/2022) ← פרטי (02/2025)",
    "bodyType": "הצ'בק",
    "brand_tier": "Standard",
    "fuelType": "חשמל/בנזין",
    "color": "שחור מטלי",
    "onRoadDate": "2022-8",
    "importer": "קאר איסט יבוא רכב בע\"מ",
    "originality": null,
    "colorChanged": "לא",
    "tiresChanged": "לא",
    "lpgAdded": "לא",
    "safetyScore": 3.0,
    "greenIndex": 72.0,
    "emissionGroup": 2.0,
    "f_agefuel": 0.633,
    "f_own": 0.95,
    "f_mile": 1.017,
    "f_body": 1.0,
    "f_brand": 1.0,
    "f_trim": 1.0,
    "f_safety": 0.96,
    "f_recall": 1.0,
    "f_test": 1.0,
    "f_emiss": 1.0,
    "f_orig": 1.0,
    "f_lpg": 1.0,
    "f_par": 1.0,
    "f_taxi": 1.0,
    "f_exp": 1.0,
    "factor": 0.587,
    "low": 87000.0,
    "mid": 99000.0,
    "high": 111000.0,
    "conf": 1.0,
    "yad2": 120500.0,
    "delta_yad2_pct": 0.2171717172,
    "levi": 120500.0,
    "delta_levi_pct": 0.2171717172,
    "notes": null
  },
  {
    "plate": "71495801",
    "mfg": "רובר אנגליה",
    "model": "RANGE  R.SPORT",
    "year": 2019.0,
    "trim": "PHEV HSE DYN",
    "country": "IL",
    "price_at_reg": 677000.0,
    "km": 27101.0,
    "age": 6.89,
    "ownership": "פרטי",
    "hand": 1.0,
    "hand_history": "פרטי (07/2019)",
    "bodyType": "פנאי-שטח",
    "brand_tier": "Standard",
    "fuelType": "חשמל/בנזין",
    "color": "שנהב לבן",
    "onRoadDate": "2019-7",
    "importer": "חברת המזרח",
    "originality": null,
    "colorChanged": "לא",
    "tiresChanged": "לא",
    "lpgAdded": "לא",
    "safetyScore": 2.0,
    "greenIndex": 110.0,
    "emissionGroup": 2.0,
    "f_agefuel": 0.484,
    "f_own": 1.0,
    "f_mile": 1.12,
    "f_body": 1.05,
    "f_brand": 1.0,
    "f_trim": 1.0,
    "f_safety": 0.96,
    "f_recall": 1.0,
    "f_test": 1.0,
    "f_emiss": 1.0,
    "f_orig": 1.0,
    "f_lpg": 1.0,
    "f_par": 1.0,
    "f_taxi": 1.0,
    "f_exp": 1.0,
    "factor": 0.546,
    "low": 325000.0,
    "mid": 369000.0,
    "high": 413000.0,
    "conf": 1.0,
    "yad2": 255300.0,
    "delta_yad2_pct": -0.3081300813,
    "levi": 246980.0,
    "delta_levi_pct": -0.3306775068,
    "notes": null
  },
  {
    "plate": "32719704",
    "mfg": "צ'רי סין",
    "model": "FX EV",
    "year": 2025.0,
    "trim": "COMFORT",
    "country": "IL",
    "price_at_reg": 164990.0,
    "km": 0.0,
    "age": 0.89,
    "ownership": "פרטי",
    "hand": 1.0,
    "hand_history": "פרטי (05/2025)",
    "bodyType": "הצ'בק",
    "brand_tier": "Chinese-IL",
    "fuelType": "חשמל",
    "color": "שחור מטלי",
    "onRoadDate": "2025-5",
    "importer": "קרסו מוטורס בע\"מ",
    "originality": null,
    "colorChanged": "לא",
    "tiresChanged": "לא",
    "lpgAdded": "לא",
    "safetyScore": 7.0,
    "greenIndex": null,
    "emissionGroup": null,
    "f_agefuel": 0.626,
    "f_own": 1.0,
    "f_mile": 1.0,
    "f_body": 1.0,
    "f_brand": 0.85,
    "f_trim": 1.0,
    "f_safety": 1.02,
    "f_recall": 1.0,
    "f_test": 1.0,
    "f_emiss": 1.0,
    "f_orig": 1.0,
    "f_lpg": 1.0,
    "f_par": 1.0,
    "f_taxi": 1.0,
    "f_exp": 1.0,
    "factor": 0.543,
    "low": 78000.0,
    "mid": 89500.0,
    "high": 100000.0,
    "conf": 0.9,
    "yad2": 137600.0,
    "delta_yad2_pct": 0.5374301676,
    "levi": 128340.0,
    "delta_levi_pct": 0.4339664804,
    "notes": null
  },
  {
    "plate": "5599931",
    "mfg": "וולבו בלגיה",
    "model": "XC60 T5",
    "year": 2014.0,
    "trim": "ACTIVE",
    "country": "IL",
    "price_at_reg": 319900.0,
    "km": null,
    "age": 11.89,
    "ownership": "פרטי",
    "hand": 1.0,
    "hand_history": null,
    "bodyType": "סטיישן",
    "brand_tier": "Standard",
    "fuelType": "בנזין",
    "color": "שנהב לבן",
    "onRoadDate": "2014-3",
    "importer": "מאיר חברה למכוניות ומשאיות בע\"",
    "originality": null,
    "colorChanged": null,
    "tiresChanged": null,
    "lpgAdded": null,
    "safetyScore": null,
    "greenIndex": 315.0,
    "emissionGroup": 15.0,
    "f_agefuel": 0.301,
    "f_own": 1.0,
    "f_mile": 1.0,
    "f_body": 1.0,
    "f_brand": 1.0,
    "f_trim": 1.0,
    "f_safety": 1.0,
    "f_recall": 1.0,
    "f_test": 0.94,
    "f_emiss": 1.0,
    "f_orig": 1.0,
    "f_lpg": 1.0,
    "f_par": 1.0,
    "f_taxi": 1.0,
    "f_exp": 1.0,
    "factor": 0.283,
    "low": 78000.0,
    "mid": 90000.0,
    "high": 102000.0,
    "conf": 0.85,
    "yad2": 44300.0,
    "delta_yad2_pct": -0.5077777778,
    "levi": 44000.0,
    "delta_levi_pct": -0.5111111111,
    "notes": null
  },
  {
    "plate": "55057701",
    "mfg": "מרצדס בנץ ארהב",
    "model": "GLE350D  4MATIC",
    "year": 2018.0,
    "trim": "PREMIUM DS",
    "country": "IL",
    "price_at_reg": 605000.0,
    "km": 119214.0,
    "age": 7.52,
    "ownership": "פרטי",
    "hand": 3.0,
    "hand_history": "פרטי (10/2018) ← סוחר (06/2021) ← פרטי (06/2021)",
    "bodyType": "פנאי-שטח",
    "brand_tier": "Premium-German",
    "fuelType": "דיזל",
    "color": "שנהב לבן",
    "onRoadDate": "2018-10",
    "importer": "כלמוביל מרצדס",
    "originality": null,
    "colorChanged": "לא",
    "tiresChanged": "לא",
    "lpgAdded": "לא",
    "safetyScore": 1.0,
    "greenIndex": 402.0,
    "emissionGroup": 15.0,
    "f_agefuel": 0.438,
    "f_own": 0.9,
    "f_mile": 0.987,
    "f_body": 1.05,
    "f_brand": 0.95,
    "f_trim": 1.03,
    "f_safety": 0.96,
    "f_recall": 1.0,
    "f_test": 1.0,
    "f_emiss": 1.0,
    "f_orig": 1.0,
    "f_lpg": 1.0,
    "f_par": 1.0,
    "f_taxi": 1.0,
    "f_exp": 1.0,
    "factor": 0.384,
    "low": 204000.0,
    "mid": 232000.0,
    "high": 260000.0,
    "conf": 1.0,
    "yad2": 260700.0,
    "delta_yad2_pct": 0.1237068966,
    "levi": 154000.0,
    "delta_levi_pct": -0.3362068966,
    "notes": null
  },
  {
    "plate": "52876104",
    "mfg": "קיה קוריאה",
    "model": "PICANTO",
    "year": 2026.0,
    "trim": "LX PLUS",
    "country": "IL",
    "price_at_reg": 109900.0,
    "km": 0.0,
    "age": 0.0,
    "ownership": "השכרה",
    "hand": 1.0,
    "hand_history": "השכרה (02/2026)",
    "bodyType": "הצ'בק",
    "brand_tier": "Korean-IL",
    "fuelType": "בנזין",
    "color": "שנהב לבן",
    "onRoadDate": "2026-2",
    "importer": "טל - קאר",
    "originality": "השכרה",
    "colorChanged": "לא",
    "tiresChanged": "לא",
    "lpgAdded": "לא",
    "safetyScore": 1.0,
    "greenIndex": 201.0,
    "emissionGroup": 11.0,
    "f_agefuel": 0.87,
    "f_own": 0.82,
    "f_mile": 1.0,
    "f_body": 1.0,
    "f_brand": 1.04,
    "f_trim": 1.0,
    "f_safety": 0.96,
    "f_recall": 1.0,
    "f_test": 1.0,
    "f_emiss": 1.0,
    "f_orig": 1.0,
    "f_lpg": 1.0,
    "f_par": 1.0,
    "f_taxi": 1.0,
    "f_exp": 1.0,
    "factor": 0.712,
    "low": 68000.0,
    "mid": 78000.0,
    "high": 88000.0,
    "conf": 0.9,
    "yad2": 111700.0,
    "delta_yad2_pct": 0.4320512821,
    "levi": 88700.0,
    "delta_levi_pct": 0.1371794872,
    "notes": null
  },
  {
    "plate": "28566801",
    "mfg": "סיטרואן ספרד",
    "model": "BERLINGO",
    "year": 2018.0,
    "trim": "MAXI",
    "country": "IL",
    "price_at_reg": 138900.0,
    "km": null,
    "age": 7.89,
    "ownership": "חברה",
    "hand": 1.0,
    "hand_history": null,
    "bodyType": "סגור/משלוח",
    "brand_tier": "Weak-resale",
    "fuelType": "דיזל",
    "color": "שנהב לבן",
    "onRoadDate": "2018-5",
    "importer": "דוד לובינסקי בע\"מ",
    "originality": null,
    "colorChanged": null,
    "tiresChanged": null,
    "lpgAdded": null,
    "safetyScore": null,
    "greenIndex": 230.0,
    "emissionGroup": 14.0,
    "f_agefuel": 0.422,
    "f_own": 0.88,
    "f_mile": 1.0,
    "f_body": 1.0,
    "f_brand": 0.93,
    "f_trim": 1.0,
    "f_safety": 1.0,
    "f_recall": 1.0,
    "f_test": 1.0,
    "f_emiss": 1.0,
    "f_orig": 1.0,
    "f_lpg": 1.0,
    "f_par": 1.0,
    "f_taxi": 1.0,
    "f_exp": 1.0,
    "factor": 0.345,
    "low": 41500.0,
    "mid": 47500.0,
    "high": 54000.0,
    "conf": 0.85,
    "yad2": 34900.0,
    "delta_yad2_pct": -0.2652631579,
    "levi": null,
    "delta_levi_pct": null,
    "notes": null
  },
  {
    "plate": "2802975",
    "mfg": "שברולט ד.קוריא",
    "model": "CRUZE 1.6 LS",
    "year": 2011.0,
    "trim": "LS",
    "country": "IL",
    "price_at_reg": 120000.0,
    "km": null,
    "age": 14.89,
    "ownership": "פרטי",
    "hand": 1.0,
    "hand_history": null,
    "bodyType": "סדאן",
    "brand_tier": "Standard",
    "fuelType": "בנזין",
    "color": "אפור",
    "onRoadDate": "2011-6",
    "importer": "יוניברסל מוטורס ישראל בע\"מ",
    "originality": null,
    "colorChanged": null,
    "tiresChanged": null,
    "lpgAdded": null,
    "safetyScore": null,
    "greenIndex": 312.0,
    "emissionGroup": 15.0,
    "f_agefuel": 0.219,
    "f_own": 1.0,
    "f_mile": 1.0,
    "f_body": 1.0,
    "f_brand": 1.0,
    "f_trim": 1.0,
    "f_safety": 1.0,
    "f_recall": 1.0,
    "f_test": 1.0,
    "f_emiss": 1.0,
    "f_orig": 1.0,
    "f_lpg": 1.0,
    "f_par": 1.0,
    "f_taxi": 1.0,
    "f_exp": 1.0,
    "factor": 0.219,
    "low": 22500.0,
    "mid": 26000.0,
    "high": 29500.0,
    "conf": 0.85,
    "yad2": 8000.0,
    "delta_yad2_pct": -0.6923076923,
    "levi": null,
    "delta_levi_pct": null,
    "notes": null
  },
  {
    "plate": "33567401",
    "mfg": "מזדה יפן",
    "model": "CX-5",
    "year": 2018.0,
    "trim": "LUXURY",
    "country": "IL",
    "price_at_reg": 179000.0,
    "km": 69200.0,
    "age": 7.89,
    "ownership": "פרטי",
    "hand": 3.0,
    "hand_history": "פרטי (06/2018) ← סוחר (06/2021) ← פרטי (06/2021)",
    "bodyType": "פנאי-שטח",
    "brand_tier": "Standard",
    "fuelType": "בנזין",
    "color": "שחור",
    "onRoadDate": "2018-6",
    "importer": "דלק מוטורס בע\"מ",
    "originality": null,
    "colorChanged": "לא",
    "tiresChanged": "לא",
    "lpgAdded": "לא",
    "safetyScore": 1.0,
    "greenIndex": 260.0,
    "emissionGroup": 15.0,
    "f_agefuel": 0.458,
    "f_own": 0.9,
    "f_mile": 1.098,
    "f_body": 1.05,
    "f_brand": 1.0,
    "f_trim": 1.03,
    "f_safety": 0.96,
    "f_recall": 1.0,
    "f_test": 1.0,
    "f_emiss": 1.0,
    "f_orig": 1.0,
    "f_lpg": 1.0,
    "f_par": 1.0,
    "f_taxi": 1.0,
    "f_exp": 1.0,
    "factor": 0.47,
    "low": 74000.0,
    "mid": 84000.0,
    "high": 94000.0,
    "conf": 1.0,
    "yad2": 85100.0,
    "delta_yad2_pct": 0.0130952381,
    "levi": 88810.0,
    "delta_levi_pct": 0.05726190476,
    "notes": null
  },
  {
    "plate": "35780802",
    "mfg": "יונדאי קוריאה",
    "model": "IONIQ HYBRID",
    "year": 2021.0,
    "trim": "PREMIUM FL",
    "country": "IL",
    "price_at_reg": 143900.0,
    "km": 63053.0,
    "age": 4.89,
    "ownership": "פרטי",
    "hand": 4.0,
    "hand_history": "החכר (01/2021) ← סוחר (11/2025) ← פרטי (11/2025) ← סוחר (11/2025)",
    "bodyType": "הצ'בק",
    "brand_tier": "Korean-IL",
    "fuelType": "בנזין",
    "color": "שנהב לבן",
    "onRoadDate": "2021-1",
    "importer": "כלמוביל יונדאי",
    "originality": "החכר",
    "colorChanged": "לא",
    "tiresChanged": "לא",
    "lpgAdded": "לא",
    "safetyScore": 1.0,
    "greenIndex": 149.0,
    "emissionGroup": 3.0,
    "f_agefuel": 0.613,
    "f_own": 0.808,
    "f_mile": 1.021,
    "f_body": 1.0,
    "f_brand": 1.04,
    "f_trim": 1.03,
    "f_safety": 0.96,
    "f_recall": 1.0,
    "f_test": 1.0,
    "f_emiss": 1.0,
    "f_orig": 1.0,
    "f_lpg": 1.0,
    "f_par": 1.0,
    "f_taxi": 1.0,
    "f_exp": 1.0,
    "factor": 0.52,
    "low": 65500.0,
    "mid": 74500.0,
    "high": 83500.0,
    "conf": 1.0,
    "yad2": 88000.0,
    "delta_yad2_pct": 0.1812080537,
    "levi": 110000.0,
    "delta_levi_pct": 0.4765100671,
    "notes": null
  },
  {
    "plate": "7953975",
    "mfg": "ניסאן אנגליה",
    "model": "QASHQAI PLUS 2",
    "year": 2011.0,
    "trim": "TEKNA",
    "country": "IL",
    "price_at_reg": 215000.0,
    "km": null,
    "age": 14.43,
    "ownership": "פרטי",
    "hand": 1.0,
    "hand_history": null,
    "bodyType": "MPV",
    "brand_tier": "Standard",
    "fuelType": "בנזין",
    "color": "אפור מטל",
    "onRoadDate": "2011-11",
    "importer": "קרסו מוטורס בע\"מ",
    "originality": null,
    "colorChanged": null,
    "tiresChanged": null,
    "lpgAdded": null,
    "safetyScore": null,
    "greenIndex": 347.0,
    "emissionGroup": 15.0,
    "f_agefuel": 0.23,
    "f_own": 1.0,
    "f_mile": 1.0,
    "f_body": 0.94,
    "f_brand": 1.0,
    "f_trim": 1.0,
    "f_safety": 1.0,
    "f_recall": 1.0,
    "f_test": 1.0,
    "f_emiss": 1.0,
    "f_orig": 1.0,
    "f_lpg": 1.0,
    "f_par": 1.0,
    "f_taxi": 1.0,
    "f_exp": 1.0,
    "factor": 0.216,
    "low": 40000.0,
    "mid": 46000.0,
    "high": 52500.0,
    "conf": 0.85,
    "yad2": 24200.0,
    "delta_yad2_pct": -0.4739130435,
    "levi": 29400.0,
    "delta_levi_pct": -0.3608695652,
    "notes": null
  },
  {
    "plate": "6984137",
    "mfg": "דאציה רומניה",
    "model": "SANDERO",
    "year": 2016.0,
    "trim": "LAUREATE",
    "country": "IL",
    "price_at_reg": 69490.0,
    "km": null,
    "age": 9.89,
    "ownership": "פרטי",
    "hand": 1.0,
    "hand_history": null,
    "bodyType": "הצ'בק",
    "brand_tier": "Weak-resale",
    "fuelType": "בנזין",
    "color": "שנהב לבן",
    "onRoadDate": "2016-1",
    "importer": "קרסו מוטורס בע\"מ",
    "originality": null,
    "colorChanged": null,
    "tiresChanged": null,
    "lpgAdded": null,
    "safetyScore": null,
    "greenIndex": 213.0,
    "emissionGroup": 13.0,
    "f_agefuel": 0.371,
    "f_own": 1.0,
    "f_mile": 1.0,
    "f_body": 1.0,
    "f_brand": 0.93,
    "f_trim": 1.0,
    "f_safety": 1.0,
    "f_recall": 1.0,
    "f_test": 1.0,
    "f_emiss": 1.0,
    "f_orig": 1.0,
    "f_lpg": 1.0,
    "f_par": 1.0,
    "f_taxi": 1.0,
    "f_exp": 1.0,
    "factor": 0.345,
    "low": 20500.0,
    "mid": 23500.0,
    "high": 27000.0,
    "conf": 0.85,
    "yad2": 16000.0,
    "delta_yad2_pct": -0.3191489362,
    "levi": 19000.0,
    "delta_levi_pct": -0.1914893617,
    "notes": null
  },
  {
    "plate": "78381703",
    "mfg": "מיצובישי תאילנ",
    "model": "SPACE STAR",
    "year": 2024.0,
    "trim": "SUPREME",
    "country": "IL",
    "price_at_reg": 91990.0,
    "km": 0.0,
    "age": 1.51,
    "ownership": "פרטי",
    "hand": 1.0,
    "hand_history": "פרטי (10/2024)",
    "bodyType": "הצ'בק",
    "brand_tier": "Standard",
    "fuelType": "בנזין",
    "color": "שנהב לבן",
    "onRoadDate": "2024-10",
    "importer": "כלמוביל מיצובישי",
    "originality": null,
    "colorChanged": "לא",
    "tiresChanged": "לא",
    "lpgAdded": "לא",
    "safetyScore": 1.0,
    "greenIndex": 189.0,
    "emissionGroup": 8.0,
    "f_agefuel": 0.8,
    "f_own": 1.0,
    "f_mile": 1.0,
    "f_body": 1.0,
    "f_brand": 1.0,
    "f_trim": 1.0,
    "f_safety": 0.96,
    "f_recall": 1.0,
    "f_test": 1.0,
    "f_emiss": 1.0,
    "f_orig": 1.0,
    "f_lpg": 1.0,
    "f_par": 1.0,
    "f_taxi": 1.0,
    "f_exp": 1.0,
    "factor": 0.768,
    "low": 61500.0,
    "mid": 70500.0,
    "high": 79500.0,
    "conf": 0.9,
    "yad2": 72700.0,
    "delta_yad2_pct": 0.03120567376,
    "levi": 74700.0,
    "delta_levi_pct": 0.05957446809,
    "notes": null
  },
  {
    "plate": "5746767",
    "mfg": "סובארו יפן",
    "model": "FORESTER",
    "year": 2009.0,
    "trim": "B",
    "country": "IL",
    "price_at_reg": 179900.0,
    "km": null,
    "age": 16.89,
    "ownership": "פרטי",
    "hand": 1.0,
    "hand_history": null,
    "bodyType": "פנאי-שטח",
    "brand_tier": "Premium-reliable",
    "fuelType": "גפ\"מ",
    "color": "אפור כהה",
    "onRoadDate": "2009-5",
    "importer": "יפנאוטו חברה ישראלית לרכב בע\"מ",
    "originality": null,
    "colorChanged": null,
    "tiresChanged": null,
    "lpgAdded": null,
    "safetyScore": null,
    "greenIndex": 400.0,
    "emissionGroup": 15.0,
    "f_agefuel": 0.16,
    "f_own": 1.0,
    "f_mile": 1.0,
    "f_body": 1.05,
    "f_brand": 1.06,
    "f_trim": 1.0,
    "f_safety": 1.0,
    "f_recall": 1.0,
    "f_test": 1.0,
    "f_emiss": 1.0,
    "f_orig": 1.0,
    "f_lpg": 1.0,
    "f_par": 1.0,
    "f_taxi": 1.0,
    "f_exp": 1.0,
    "factor": 0.178,
    "low": 27500.0,
    "mid": 31500.0,
    "high": 36000.0,
    "conf": 0.85,
    "yad2": 22100.0,
    "delta_yad2_pct": -0.2984126984,
    "levi": 23600.0,
    "delta_levi_pct": -0.2507936508,
    "notes": null
  },
  {
    "plate": "15849203",
    "mfg": "מיצובישי יפן",
    "model": "ECLIPSE CROSS",
    "year": 2022.0,
    "trim": "EXECUTIVE",
    "country": "IL",
    "price_at_reg": 159900.0,
    "km": 20535.0,
    "age": 3.43,
    "ownership": "פרטי",
    "hand": 1.0,
    "hand_history": "פרטי (11/2022)",
    "bodyType": "פנאי-שטח",
    "brand_tier": "Standard",
    "fuelType": "בנזין",
    "color": "שנהב לבן",
    "onRoadDate": "2022-11",
    "importer": "כלמוביל מיצובישי",
    "originality": null,
    "colorChanged": "לא",
    "tiresChanged": "לא",
    "lpgAdded": "לא",
    "safetyScore": 2.0,
    "greenIndex": 298.0,
    "emissionGroup": 15.0,
    "f_agefuel": 0.693,
    "f_own": 1.0,
    "f_mile": 1.062,
    "f_body": 1.05,
    "f_brand": 1.0,
    "f_trim": 1.03,
    "f_safety": 0.96,
    "f_recall": 1.0,
    "f_test": 1.0,
    "f_emiss": 1.0,
    "f_orig": 1.0,
    "f_lpg": 1.0,
    "f_par": 1.0,
    "f_taxi": 1.0,
    "f_exp": 1.0,
    "factor": 0.764,
    "low": 107000.0,
    "mid": 122000.0,
    "high": 136000.0,
    "conf": 1.0,
    "yad2": 103900.0,
    "delta_yad2_pct": -0.1483606557,
    "levi": 109000.0,
    "delta_levi_pct": -0.106557377,
    "notes": null
  },
  {
    "plate": "6673713",
    "mfg": "סיטרואן ספרד",
    "model": "BERLINGO",
    "year": 2012.0,
    "trim": "COMFORT",
    "country": "IL",
    "price_at_reg": 124990.0,
    "km": null,
    "age": 13.89,
    "ownership": "פרטי",
    "hand": 1.0,
    "hand_history": null,
    "bodyType": "קומבי",
    "brand_tier": "Weak-resale",
    "fuelType": "דיזל",
    "color": "שנהב לבן",
    "onRoadDate": "2012-9",
    "importer": "דוד לובינסקי בע\"מ",
    "originality": null,
    "colorChanged": null,
    "tiresChanged": null,
    "lpgAdded": null,
    "safetyScore": null,
    "greenIndex": 478.0,
    "emissionGroup": 15.0,
    "f_agefuel": 0.224,
    "f_own": 1.0,
    "f_mile": 1.0,
    "f_body": 1.0,
    "f_brand": 0.93,
    "f_trim": 1.0,
    "f_safety": 1.0,
    "f_recall": 1.0,
    "f_test": 1.0,
    "f_emiss": 1.0,
    "f_orig": 1.0,
    "f_lpg": 1.0,
    "f_par": 1.0,
    "f_taxi": 1.0,
    "f_exp": 1.0,
    "factor": 0.208,
    "low": 22500.0,
    "mid": 26000.0,
    "high": 29000.0,
    "conf": 0.85,
    "yad2": 14900.0,
    "delta_yad2_pct": -0.4269230769,
    "levi": 20400.0,
    "delta_levi_pct": -0.2153846154,
    "notes": null
  },
  {
    "plate": "3066333",
    "mfg": "רנו טורקיה",
    "model": "CLIO",
    "year": 2015.0,
    "trim": "COLLECTION",
    "country": "IL",
    "price_at_reg": 108990.0,
    "km": null,
    "age": 10.43,
    "ownership": "סוחר",
    "hand": 1.0,
    "hand_history": null,
    "bodyType": "הצ'בק",
    "brand_tier": "Korean-IL",
    "fuelType": "בנזין",
    "color": "אדום מטל",
    "onRoadDate": "2015-11",
    "importer": "קרסו מוטורס בע\"מ",
    "originality": null,
    "colorChanged": null,
    "tiresChanged": null,
    "lpgAdded": null,
    "safetyScore": null,
    "greenIndex": 241.0,
    "emissionGroup": 14.0,
    "f_agefuel": 0.35,
    "f_own": 1.0,
    "f_mile": 1.0,
    "f_body": 1.0,
    "f_brand": 1.04,
    "f_trim": 1.0,
    "f_safety": 1.0,
    "f_recall": 1.0,
    "f_test": 1.0,
    "f_emiss": 1.0,
    "f_orig": 1.0,
    "f_lpg": 1.0,
    "f_par": 1.0,
    "f_taxi": 1.0,
    "f_exp": 1.0,
    "factor": 0.364,
    "low": 34000.0,
    "mid": 39500.0,
    "high": 44500.0,
    "conf": 0.85,
    "yad2": 17800.0,
    "delta_yad2_pct": -0.5493670886,
    "levi": 24000.0,
    "delta_levi_pct": -0.3924050633,
    "notes": null
  },
  {
    "plate": "46321803",
    "mfg": "טויוטה צרפת",
    "model": "YARIS CROSS HSD",
    "year": 2023.0,
    "trim": "ECO",
    "country": "IL",
    "price_at_reg": 145990.0,
    "km": 67435.0,
    "age": 2.89,
    "ownership": "סוחר",
    "hand": 3.0,
    "hand_history": "החכר (07/2023) ← סוחר (03/2026) ← סוחר (03/2026)",
    "bodyType": "פנאי-שטח",
    "brand_tier": "Premium-reliable",
    "fuelType": "בנזין",
    "color": "שנהב לבן",
    "onRoadDate": "2023-7",
    "importer": "יוניון מוטורס בע\"מ",
    "originality": "החכר",
    "colorChanged": "לא",
    "tiresChanged": "לא",
    "lpgAdded": "לא",
    "safetyScore": 2.0,
    "greenIndex": 147.0,
    "emissionGroup": 3.0,
    "f_agefuel": 0.724,
    "f_own": 0.836,
    "f_mile": 0.952,
    "f_body": 1.05,
    "f_brand": 1.06,
    "f_trim": 1.0,
    "f_safety": 0.96,
    "f_recall": 1.0,
    "f_test": 1.0,
    "f_emiss": 1.0,
    "f_orig": 1.0,
    "f_lpg": 1.0,
    "f_par": 1.0,
    "f_taxi": 1.0,
    "f_exp": 1.0,
    "factor": 0.615,
    "low": 79000.0,
    "mid": 89500.0,
    "high": 100000.0,
    "conf": 1.0,
    "yad2": 112700.0,
    "delta_yad2_pct": 0.2592178771,
    "levi": 113800.0,
    "delta_levi_pct": 0.2715083799,
    "notes": null
  },
  {
    "plate": "30524401",
    "mfg": "פורד ארה\"ב",
    "model": "EXPLORER LIMITE",
    "year": 2018.0,
    "trim": "LUXURY",
    "country": "IL",
    "price_at_reg": 329000.0,
    "km": 85879.0,
    "age": 7.89,
    "ownership": "סוחר",
    "hand": 3.0,
    "hand_history": "פרטי (05/2018) ← חברה (03/2023) ← סוחר (02/2026)",
    "bodyType": "פנאי-שטח",
    "brand_tier": "Standard",
    "fuelType": "בנזין",
    "color": "שנהב לבן",
    "onRoadDate": "2018-5",
    "importer": "דלק מוטורס בע\"מ",
    "originality": null,
    "colorChanged": "לא",
    "tiresChanged": "לא",
    "lpgAdded": "לא",
    "safetyScore": 1.0,
    "greenIndex": 604.0,
    "emissionGroup": 15.0,
    "f_agefuel": 0.458,
    "f_own": 0.9,
    "f_mile": 1.065,
    "f_body": 1.05,
    "f_brand": 1.0,
    "f_trim": 1.03,
    "f_safety": 0.96,
    "f_recall": 1.0,
    "f_test": 1.0,
    "f_emiss": 1.0,
    "f_orig": 1.0,
    "f_lpg": 1.0,
    "f_par": 1.0,
    "f_taxi": 1.0,
    "f_exp": 1.0,
    "factor": 0.456,
    "low": 131000.0,
    "mid": 149000.0,
    "high": 167000.0,
    "conf": 1.0,
    "yad2": 97500.0,
    "delta_yad2_pct": -0.3456375839,
    "levi": 110090.0,
    "delta_levi_pct": -0.2611409396,
    "notes": null
  },
  {
    "plate": "30607202",
    "mfg": "פיג'ו צרפת",
    "model": "3008",
    "year": 2021.0,
    "trim": "PREMIUM",
    "country": "IL",
    "price_at_reg": 169990.0,
    "km": 85057.0,
    "age": 4.89,
    "ownership": "פרטי",
    "hand": 6.0,
    "hand_history": "החכר (01/2021) ← סוחר (05/2022) ← פרטי (06/2022) ← סוחר (01/2023) ← סוחר (01/2023) ← פרטי (03/2023)",
    "bodyType": "פנאי-שטח",
    "brand_tier": "Weak-resale",
    "fuelType": "בנזין",
    "color": "שנהב לבן",
    "onRoadDate": "2021-1",
    "importer": "דוד לובינסקי בע\"מ",
    "originality": null,
    "colorChanged": "לא",
    "tiresChanged": "לא",
    "lpgAdded": "לא",
    "safetyScore": 2.0,
    "greenIndex": 265.0,
    "emissionGroup": 15.0,
    "f_agefuel": 0.613,
    "f_own": 0.771,
    "f_mile": 0.976,
    "f_body": 1.05,
    "f_brand": 0.93,
    "f_trim": 1.03,
    "f_safety": 0.96,
    "f_recall": 1.0,
    "f_test": 1.0,
    "f_emiss": 1.0,
    "f_orig": 1.0,
    "f_lpg": 1.0,
    "f_par": 1.0,
    "f_taxi": 1.0,
    "f_exp": 1.0,
    "factor": 0.446,
    "low": 66500.0,
    "mid": 75500.0,
    "high": 84500.0,
    "conf": 1.0,
    "yad2": 81200.0,
    "delta_yad2_pct": 0.07549668874,
    "levi": 98000.0,
    "delta_levi_pct": 0.298013245,
    "notes": null
  },
  {
    "plate": "4382071",
    "mfg": "מזדה יפן",
    "model": "MAZDA 3",
    "year": 2010.0,
    "trim": "ACTIVE",
    "country": "IL",
    "price_at_reg": 118500.0,
    "km": null,
    "age": 15.35,
    "ownership": "פרטי",
    "hand": 1.0,
    "hand_history": null,
    "bodyType": "סדאן",
    "brand_tier": "Standard",
    "fuelType": "בנזין",
    "color": "אפור",
    "onRoadDate": "2010-12",
    "importer": "דלק מוטורס בע\"מ",
    "originality": null,
    "colorChanged": null,
    "tiresChanged": null,
    "lpgAdded": null,
    "safetyScore": null,
    "greenIndex": 309.0,
    "emissionGroup": 15.0,
    "f_agefuel": 0.209,
    "f_own": 1.0,
    "f_mile": 1.0,
    "f_body": 1.0,
    "f_brand": 1.0,
    "f_trim": 1.0,
    "f_safety": 1.0,
    "f_recall": 1.0,
    "f_test": 0.94,
    "f_emiss": 1.0,
    "f_orig": 1.0,
    "f_lpg": 1.0,
    "f_par": 1.0,
    "f_taxi": 1.0,
    "f_exp": 1.0,
    "factor": 0.196,
    "low": 20000.0,
    "mid": 23000.0,
    "high": 26000.0,
    "conf": 0.85,
    "yad2": 11800.0,
    "delta_yad2_pct": -0.4869565217,
    "levi": 12000.0,
    "delta_levi_pct": -0.4782608696,
    "notes": null
  },
  {
    "plate": "8486338",
    "mfg": "קיה סלובקיה",
    "model": "SPORTAGE",
    "year": 2016.0,
    "trim": "URBAN",
    "country": "IL",
    "price_at_reg": 137900.0,
    "km": null,
    "age": 9.89,
    "ownership": "סוחר",
    "hand": 1.0,
    "hand_history": null,
    "bodyType": "פנאי-שטח",
    "brand_tier": "Korean-IL",
    "fuelType": "בנזין",
    "color": "זהוב",
    "onRoadDate": "2016-6",
    "importer": "טל - קאר",
    "originality": null,
    "colorChanged": null,
    "tiresChanged": null,
    "lpgAdded": null,
    "safetyScore": 1.0,
    "greenIndex": 313.0,
    "emissionGroup": 15.0,
    "f_agefuel": 0.371,
    "f_own": 1.0,
    "f_mile": 1.0,
    "f_body": 1.05,
    "f_brand": 1.04,
    "f_trim": 1.0,
    "f_safety": 0.96,
    "f_recall": 1.0,
    "f_test": 1.0,
    "f_emiss": 1.0,
    "f_orig": 1.0,
    "f_lpg": 1.0,
    "f_par": 1.0,
    "f_taxi": 1.0,
    "f_exp": 1.0,
    "factor": 0.389,
    "low": 46500.0,
    "mid": 53500.0,
    "high": 60500.0,
    "conf": 0.85,
    "yad2": 45100.0,
    "delta_yad2_pct": -0.1570093458,
    "levi": 51000.0,
    "delta_levi_pct": -0.04672897196,
    "notes": null
  },
  {
    "plate": "63411102",
    "mfg": "יונדאי קוריאה",
    "model": "ELANTRA HEV",
    "year": 2022.0,
    "trim": "SUPREME",
    "country": "IL",
    "price_at_reg": 149900.0,
    "km": 72419.0,
    "age": 3.89,
    "ownership": "סוחר",
    "hand": 5.0,
    "hand_history": "פרטי (01/2022) ← סוחר (06/2024) ← פרטי (07/2024) ← פרטי (05/2025) ← סוחר (03/2026)",
    "bodyType": "סדאן",
    "brand_tier": "Korean-IL",
    "fuelType": "בנזין",
    "color": "כסוף כהה",
    "onRoadDate": "2022-1",
    "importer": "כלמוביל יונדאי",
    "originality": null,
    "colorChanged": "לא",
    "tiresChanged": "לא",
    "lpgAdded": "לא",
    "safetyScore": 6.0,
    "greenIndex": 154.0,
    "emissionGroup": 4.0,
    "f_agefuel": 0.667,
    "f_own": 0.82,
    "f_mile": 0.972,
    "f_body": 1.0,
    "f_brand": 1.04,
    "f_trim": 1.0,
    "f_safety": 1.0,
    "f_recall": 1.0,
    "f_test": 1.0,
    "f_emiss": 1.0,
    "f_orig": 1.0,
    "f_lpg": 1.0,
    "f_par": 1.0,
    "f_taxi": 1.0,
    "f_exp": 1.0,
    "factor": 0.552,
    "low": 72500.0,
    "mid": 82500.0,
    "high": 92500.0,
    "conf": 1.0,
    "yad2": 116800.0,
    "delta_yad2_pct": 0.4157575758,
    "levi": 130290.0,
    "delta_levi_pct": 0.5792727273,
    "notes": null
  },
  {
    "plate": "46963902",
    "mfg": "ניסאן אנגליה",
    "model": "QASHQAI",
    "year": 2021.0,
    "trim": "TECH DESIGN",
    "country": "IL",
    "price_at_reg": 158990.0,
    "km": 85272.0,
    "age": 4.89,
    "ownership": "סוחר",
    "hand": 2.0,
    "hand_history": "פרטי (02/2021) ← סוחר (12/2025)",
    "bodyType": "פנאי-שטח",
    "brand_tier": "Standard",
    "fuelType": "בנזין",
    "color": "אפור מטל",
    "onRoadDate": "2021-2",
    "importer": "קרסו מוטורס בע\"מ",
    "originality": null,
    "colorChanged": "לא",
    "tiresChanged": "לא",
    "lpgAdded": "לא",
    "safetyScore": 1.0,
    "greenIndex": 257.0,
    "emissionGroup": 15.0,
    "f_agefuel": 0.613,
    "f_own": 0.95,
    "f_mile": 0.976,
    "f_body": 1.05,
    "f_brand": 1.0,
    "f_trim": 1.0,
    "f_safety": 0.96,
    "f_recall": 1.0,
    "f_test": 0.94,
    "f_emiss": 1.0,
    "f_orig": 1.0,
    "f_lpg": 1.0,
    "f_par": 1.0,
    "f_taxi": 1.0,
    "f_exp": 1.0,
    "factor": 0.539,
    "low": 75000.0,
    "mid": 85500.0,
    "high": 95500.0,
    "conf": 1.0,
    "yad2": 93000.0,
    "delta_yad2_pct": 0.08771929825,
    "levi": 102420.0,
    "delta_levi_pct": 0.1978947368,
    "notes": null
  },
  {
    "plate": "5206026",
    "mfg": "טויוטה טורקיה",
    "model": "COROLLA HSD SDN",
    "year": 2022.0,
    "trim": "SENSE",
    "country": "IL",
    "price_at_reg": 145990.0,
    "km": null,
    "age": 3.89,
    "ownership": "פרטי",
    "hand": 1.0,
    "hand_history": null,
    "bodyType": "סדאן",
    "brand_tier": "Premium-reliable",
    "fuelType": "בנזין",
    "color": "שנהב לבן",
    "onRoadDate": "2022-1",
    "importer": "יוניון מוטורס בע\"מ",
    "originality": null,
    "colorChanged": null,
    "tiresChanged": null,
    "lpgAdded": null,
    "safetyScore": 1.0,
    "greenIndex": 144.0,
    "emissionGroup": 3.0,
    "f_agefuel": 0.667,
    "f_own": 1.0,
    "f_mile": 1.0,
    "f_body": 1.0,
    "f_brand": 1.06,
    "f_trim": 1.0,
    "f_safety": 0.96,
    "f_recall": 1.0,
    "f_test": 0.94,
    "f_emiss": 1.0,
    "f_orig": 1.0,
    "f_lpg": 1.0,
    "f_par": 1.0,
    "f_taxi": 1.0,
    "f_exp": 1.0,
    "factor": 0.638,
    "low": 80500.0,
    "mid": 93000.0,
    "high": 105000.0,
    "conf": 0.85,
    "yad2": 104000.0,
    "delta_yad2_pct": 0.1182795699,
    "levi": 115140.0,
    "delta_levi_pct": 0.2380645161,
    "notes": null
  },
  {
    "plate": "88748201",
    "mfg": "מרצדס בנץ ספרד",
    "model": "VITO",
    "year": 2020.0,
    "trim": "114T.BASE FL",
    "country": "IL",
    "price_at_reg": 274950.0,
    "km": 67037.0,
    "age": 5.51,
    "ownership": "פרטי",
    "hand": 1.0,
    "hand_history": "פרטי (10/2020)",
    "bodyType": "קומבי",
    "brand_tier": "Premium-German",
    "fuelType": "דיזל",
    "color": "שחור מטלי",
    "onRoadDate": "2020-10",
    "importer": "כלמוביל מרצדס",
    "originality": null,
    "colorChanged": "לא",
    "tiresChanged": "כן",
    "lpgAdded": "לא",
    "safetyScore": null,
    "greenIndex": 284.0,
    "emissionGroup": 15.0,
    "f_agefuel": 0.536,
    "f_own": 1.0,
    "f_mile": 1.031,
    "f_body": 1.0,
    "f_brand": 0.95,
    "f_trim": 0.98,
    "f_safety": 1.0,
    "f_recall": 1.0,
    "f_test": 1.0,
    "f_emiss": 1.0,
    "f_orig": 0.98,
    "f_lpg": 1.0,
    "f_par": 1.0,
    "f_taxi": 1.0,
    "f_exp": 1.0,
    "factor": 0.504,
    "low": 121000.0,
    "mid": 138000.0,
    "high": 155000.0,
    "conf": 1.0,
    "yad2": 147100.0,
    "delta_yad2_pct": 0.06594202899,
    "levi": null,
    "delta_levi_pct": null,
    "notes": null
  },
  {
    "plate": "26589903",
    "mfg": "פולקסווגן-ספרד",
    "model": "POLO",
    "year": 2023.0,
    "trim": "STYLE",
    "country": "IL",
    "price_at_reg": 127900.0,
    "km": 0.0,
    "age": 2.89,
    "ownership": "פרטי",
    "hand": 1.0,
    "hand_history": "פרטי (06/2023)",
    "bodyType": "הצ'בק",
    "brand_tier": "Standard",
    "fuelType": "בנזין",
    "color": "שנהב לבן",
    "onRoadDate": "2023-6",
    "importer": "צ'מפיון מוטורס בע\"מ",
    "originality": null,
    "colorChanged": "לא",
    "tiresChanged": "לא",
    "lpgAdded": "לא",
    "safetyScore": 3.0,
    "greenIndex": 225.0,
    "emissionGroup": 14.0,
    "f_agefuel": 0.724,
    "f_own": 1.0,
    "f_mile": 1.0,
    "f_body": 1.0,
    "f_brand": 1.0,
    "f_trim": 1.0,
    "f_safety": 0.96,
    "f_recall": 1.0,
    "f_test": 0.94,
    "f_emiss": 1.0,
    "f_orig": 1.0,
    "f_lpg": 1.0,
    "f_par": 1.0,
    "f_taxi": 1.0,
    "f_exp": 1.0,
    "factor": 0.653,
    "low": 72500.0,
    "mid": 83500.0,
    "high": 94000.0,
    "conf": 0.9,
    "yad2": 96600.0,
    "delta_yad2_pct": 0.1568862275,
    "levi": 89000.0,
    "delta_levi_pct": 0.06586826347,
    "notes": null
  },
  {
    "plate": "23977802",
    "mfg": "ניסאן מקסיקו",
    "model": "SENTRA",
    "year": 2020.0,
    "trim": "SR",
    "country": "IL",
    "price_at_reg": 134990.0,
    "km": null,
    "age": 5.43,
    "ownership": "פרטי",
    "hand": 1.0,
    "hand_history": null,
    "bodyType": "סדאן",
    "brand_tier": "Standard",
    "fuelType": "בנזין",
    "color": "כסף מטלי",
    "onRoadDate": "2020-11",
    "importer": "קרסו מוטורס בע\"מ",
    "originality": null,
    "colorChanged": null,
    "tiresChanged": null,
    "lpgAdded": null,
    "safetyScore": null,
    "greenIndex": 237.0,
    "emissionGroup": 14.0,
    "f_agefuel": 0.586,
    "f_own": 1.0,
    "f_mile": 1.0,
    "f_body": 1.0,
    "f_brand": 1.0,
    "f_trim": 1.0,
    "f_safety": 1.0,
    "f_recall": 1.0,
    "f_test": 1.0,
    "f_emiss": 1.0,
    "f_orig": 1.0,
    "f_lpg": 1.0,
    "f_par": 1.0,
    "f_taxi": 1.0,
    "f_exp": 1.0,
    "factor": 0.586,
    "low": 68500.0,
    "mid": 79000.0,
    "high": 89500.0,
    "conf": 0.85,
    "yad2": 51200.0,
    "delta_yad2_pct": -0.3518987342,
    "levi": 68000.0,
    "delta_levi_pct": -0.1392405063,
    "notes": null
  },
  {
    "plate": "66180203",
    "mfg": "סובארו יפן",
    "model": "CROSSTREK",
    "year": 2024.0,
    "trim": "TOURING",
    "country": "IL",
    "price_at_reg": 164900.0,
    "km": 0.0,
    "age": 1.89,
    "ownership": "פרטי",
    "hand": 1.0,
    "hand_history": "פרטי (02/2024)",
    "bodyType": "פנאי-שטח",
    "brand_tier": "Premium-reliable",
    "fuelType": "בנזין",
    "color": "כחול",
    "onRoadDate": "2024-2",
    "importer": "יפנאוטו חברה ישראלית לרכב בע\"מ",
    "originality": null,
    "colorChanged": "לא",
    "tiresChanged": "לא",
    "lpgAdded": "לא",
    "safetyScore": 1.0,
    "greenIndex": 266.0,
    "emissionGroup": 15.0,
    "f_agefuel": 0.778,
    "f_own": 1.0,
    "f_mile": 1.0,
    "f_body": 1.05,
    "f_brand": 1.06,
    "f_trim": 1.0,
    "f_safety": 0.96,
    "f_recall": 1.0,
    "f_test": 1.0,
    "f_emiss": 1.0,
    "f_orig": 1.0,
    "f_lpg": 1.0,
    "f_par": 1.0,
    "f_taxi": 1.0,
    "f_exp": 1.0,
    "factor": 0.832,
    "low": 119000.0,
    "mid": 137000.0,
    "high": 154000.0,
    "conf": 0.9,
    "yad2": 131800.0,
    "delta_yad2_pct": -0.03795620438,
    "levi": 120290.0,
    "delta_levi_pct": -0.1219708029,
    "notes": null
  },
  {
    "plate": "28011101",
    "mfg": "פיג'ו צרפת",
    "model": "308",
    "year": 2018.0,
    "trim": "PREMIUM",
    "country": "IL",
    "price_at_reg": 129900.0,
    "km": 95170.0,
    "age": 7.89,
    "ownership": "פרטי",
    "hand": 1.0,
    "hand_history": "פרטי (01/2018)",
    "bodyType": "הצ'בק",
    "brand_tier": "Weak-resale",
    "fuelType": "בנזין",
    "color": "שחור",
    "onRoadDate": "2018-1",
    "importer": "דוד לובינסקי בע\"מ",
    "originality": null,
    "colorChanged": "לא",
    "tiresChanged": "לא",
    "lpgAdded": "לא",
    "safetyScore": null,
    "greenIndex": 235.0,
    "emissionGroup": 14.0,
    "f_agefuel": 0.458,
    "f_own": 1.0,
    "f_mile": 1.046,
    "f_body": 1.0,
    "f_brand": 0.93,
    "f_trim": 1.03,
    "f_safety": 1.0,
    "f_recall": 1.0,
    "f_test": 1.0,
    "f_emiss": 1.0,
    "f_orig": 1.0,
    "f_lpg": 1.0,
    "f_par": 1.0,
    "f_taxi": 1.0,
    "f_exp": 1.0,
    "factor": 0.459,
    "low": 52000.0,
    "mid": 59500.0,
    "high": 66500.0,
    "conf": 1.0,
    "yad2": 40700.0,
    "delta_yad2_pct": -0.3159663866,
    "levi": 37370.0,
    "delta_levi_pct": -0.3719327731,
    "notes": null
  },
  {
    "plate": "71912603",
    "mfg": "זיקר",
    "model": "ZEEKR X",
    "year": 2024.0,
    "trim": "KRYPTON",
    "country": "IL",
    "price_at_reg": 204990.0,
    "km": 0.0,
    "age": 1.89,
    "ownership": "פרטי",
    "hand": 1.0,
    "hand_history": "פרטי (02/2024)",
    "bodyType": "פנאי-שטח",
    "brand_tier": "Standard",
    "fuelType": "חשמל",
    "color": "אפור בהיר מטלי",
    "onRoadDate": "2024-2",
    "importer": "גיאו מוביליטי בע\"מ",
    "originality": null,
    "colorChanged": "לא",
    "tiresChanged": "לא",
    "lpgAdded": "לא",
    "safetyScore": 10.0,
    "greenIndex": null,
    "emissionGroup": null,
    "f_agefuel": 0.662,
    "f_own": 1.0,
    "f_mile": 1.0,
    "f_body": 1.05,
    "f_brand": 1.0,
    "f_trim": 1.0,
    "f_safety": 1.0,
    "f_recall": 1.0,
    "f_test": 0.94,
    "f_emiss": 1.0,
    "f_orig": 1.0,
    "f_lpg": 1.0,
    "f_par": 1.0,
    "f_taxi": 1.0,
    "f_exp": 1.0,
    "factor": 0.653,
    "low": 116000.0,
    "mid": 133000.0,
    "high": 150000.0,
    "conf": 0.9,
    "yad2": 144100.0,
    "delta_yad2_pct": 0.08345864662,
    "levi": 154600.0,
    "delta_levi_pct": 0.162406015,
    "notes": null
  },
  {
    "plate": "1154867",
    "mfg": "פיאט פולין",
    "model": "FIAT 500 1.2",
    "year": 2009.0,
    "trim": "POP",
    "country": "IL",
    "price_at_reg": 109990.0,
    "km": null,
    "age": 16.89,
    "ownership": "פרטי",
    "hand": 1.0,
    "hand_history": null,
    "bodyType": "הצ'בק",
    "brand_tier": "Weak-resale",
    "fuelType": "בנזין",
    "color": "כחול",
    "onRoadDate": "2009-6",
    "importer": "סמלת מוטורס בע\"מ",
    "originality": null,
    "colorChanged": null,
    "tiresChanged": null,
    "lpgAdded": null,
    "safetyScore": null,
    "greenIndex": 229.0,
    "emissionGroup": 14.0,
    "f_agefuel": 0.178,
    "f_own": 1.0,
    "f_mile": 1.0,
    "f_body": 1.0,
    "f_brand": 0.93,
    "f_trim": 1.0,
    "f_safety": 1.0,
    "f_recall": 1.0,
    "f_test": 1.0,
    "f_emiss": 1.0,
    "f_orig": 1.0,
    "f_lpg": 1.0,
    "f_par": 1.0,
    "f_taxi": 1.0,
    "f_exp": 1.0,
    "factor": 0.165,
    "low": 15500.0,
    "mid": 18000.0,
    "high": 20500.0,
    "conf": 0.85,
    "yad2": 8700.0,
    "delta_yad2_pct": -0.5166666667,
    "levi": null,
    "delta_levi_pct": null,
    "notes": null
  },
  {
    "plate": "76866003",
    "mfg": "אודי מכסיקו",
    "model": "Q5",
    "year": 2024.0,
    "trim": "SLINE LUX",
    "country": "IL",
    "price_at_reg": 398900.0,
    "km": 0.0,
    "age": 1.89,
    "ownership": "פרטי",
    "hand": 1.0,
    "hand_history": "פרטי (04/2024)",
    "bodyType": "פנאי-שטח",
    "brand_tier": "Standard",
    "fuelType": "בנזין",
    "color": "שחור מטלי",
    "onRoadDate": "2024-4",
    "importer": "צ'מפיון מוטורס בע\"מ",
    "originality": null,
    "colorChanged": "לא",
    "tiresChanged": "לא",
    "lpgAdded": "לא",
    "safetyScore": 1.0,
    "greenIndex": 291.0,
    "emissionGroup": 15.0,
    "f_agefuel": 0.778,
    "f_own": 1.0,
    "f_mile": 1.0,
    "f_body": 1.05,
    "f_brand": 1.0,
    "f_trim": 1.0,
    "f_safety": 0.96,
    "f_recall": 1.0,
    "f_test": 1.0,
    "f_emiss": 1.0,
    "f_orig": 1.0,
    "f_lpg": 1.0,
    "f_par": 1.0,
    "f_taxi": 1.0,
    "f_exp": 1.0,
    "factor": 0.785,
    "low": 272000.0,
    "mid": 312000.0,
    "high": 353000.0,
    "conf": 0.9,
    "yad2": 282600.0,
    "delta_yad2_pct": -0.09423076923,
    "levi": 269200.0,
    "delta_levi_pct": -0.1371794872,
    "notes": null
  },
  {
    "plate": "7203731",
    "mfg": "קיה קוריאה",
    "model": "SOUL",
    "year": 2014.0,
    "trim": "LX",
    "country": "IL",
    "price_at_reg": 143500.0,
    "km": null,
    "age": 11.89,
    "ownership": "פרטי",
    "hand": 1.0,
    "hand_history": null,
    "bodyType": "הצ'בק",
    "brand_tier": "Korean-IL",
    "fuelType": "דיזל",
    "color": "שנהב לבן",
    "onRoadDate": "2014-7",
    "importer": "טל - קאר",
    "originality": null,
    "colorChanged": null,
    "tiresChanged": null,
    "lpgAdded": null,
    "safetyScore": null,
    "greenIndex": 469.0,
    "emissionGroup": 15.0,
    "f_agefuel": 0.277,
    "f_own": 1.0,
    "f_mile": 1.0,
    "f_body": 1.0,
    "f_brand": 1.04,
    "f_trim": 1.0,
    "f_safety": 1.0,
    "f_recall": 1.0,
    "f_test": 1.0,
    "f_emiss": 1.0,
    "f_orig": 1.0,
    "f_lpg": 1.0,
    "f_par": 1.0,
    "f_taxi": 1.0,
    "f_exp": 1.0,
    "factor": 0.288,
    "low": 35500.0,
    "mid": 41000.0,
    "high": 46500.0,
    "conf": 0.85,
    "yad2": 16800.0,
    "delta_yad2_pct": -0.5902439024,
    "levi": null,
    "delta_levi_pct": null,
    "notes": null
  },
  {
    "plate": "62940301",
    "mfg": "סקודה צ'כיה",
    "model": "KAROQ",
    "year": 2019.0,
    "trim": "STYLE",
    "country": "IL",
    "price_at_reg": 174990.0,
    "km": 174426.0,
    "age": 6.89,
    "ownership": "פרטי",
    "hand": 3.0,
    "hand_history": "פרטי (01/2019) ← פרטי (12/2022) ← פרטי (05/2025)",
    "bodyType": "פנאי-שטח",
    "brand_tier": "Standard",
    "fuelType": "דיזל",
    "color": "אפור מטל",
    "onRoadDate": "2019-1",
    "importer": "צ'מפיון מוטורס בע\"מ",
    "originality": null,
    "colorChanged": "לא",
    "tiresChanged": "לא",
    "lpgAdded": "לא",
    "safetyScore": null,
    "greenIndex": 306.0,
    "emissionGroup": 15.0,
    "f_agefuel": 0.468,
    "f_own": 0.9,
    "f_mile": 0.858,
    "f_body": 1.05,
    "f_brand": 1.0,
    "f_trim": 1.0,
    "f_safety": 1.0,
    "f_recall": 1.0,
    "f_test": 1.0,
    "f_emiss": 1.0,
    "f_orig": 1.0,
    "f_lpg": 1.0,
    "f_par": 1.0,
    "f_taxi": 1.0,
    "f_exp": 1.0,
    "factor": 0.38,
    "low": 58000.0,
    "mid": 66000.0,
    "high": 74000.0,
    "conf": 1.0,
    "yad2": 76200.0,
    "delta_yad2_pct": 0.1545454545,
    "levi": 71000.0,
    "delta_levi_pct": 0.07575757576,
    "notes": null
  },
  {
    "plate": "36443104",
    "mfg": "ג'אקו סין",
    "model": "JAECOO7 PHEV",
    "year": 2025.0,
    "trim": "PREMIUM",
    "country": "IL",
    "price_at_reg": 189990.0,
    "km": 0.0,
    "age": 0.89,
    "ownership": "ליסינג",
    "hand": 1.0,
    "hand_history": "החכר (09/2025)",
    "bodyType": "פנאי-שטח",
    "brand_tier": "Standard",
    "fuelType": "חשמל/בנזין",
    "color": "שחור",
    "onRoadDate": "2025-9",
    "importer": "כלמוביל בע\"מ",
    "originality": "החכר",
    "colorChanged": "לא",
    "tiresChanged": "לא",
    "lpgAdded": "לא",
    "safetyScore": 8.0,
    "greenIndex": 79.0,
    "emissionGroup": 2.0,
    "f_agefuel": 0.626,
    "f_own": 0.82,
    "f_mile": 1.0,
    "f_body": 1.05,
    "f_brand": 1.0,
    "f_trim": 1.03,
    "f_safety": 1.02,
    "f_recall": 1.0,
    "f_test": 1.0,
    "f_emiss": 1.0,
    "f_orig": 1.0,
    "f_lpg": 1.0,
    "f_par": 1.0,
    "f_taxi": 1.0,
    "f_exp": 1.0,
    "factor": 0.566,
    "low": 93500.0,
    "mid": 107000.0,
    "high": 121000.0,
    "conf": 0.9,
    "yad2": 169100.0,
    "delta_yad2_pct": 0.5803738318,
    "levi": 166400.0,
    "delta_levi_pct": 0.5551401869,
    "notes": null
  },
  {
    "plate": "82019002",
    "mfg": "טויוטה טורקיה",
    "model": "COROLLA HSD SDN",
    "year": 2021.0,
    "trim": "SUN",
    "country": "IL",
    "price_at_reg": 140900.0,
    "km": 105502.0,
    "age": 4.35,
    "ownership": "פרטי",
    "hand": 2.0,
    "hand_history": "החכר (12/2021) ← פרטי (08/2025)",
    "bodyType": "סדאן",
    "brand_tier": "Premium-reliable",
    "fuelType": "בנזין",
    "color": "כסף מטלי",
    "onRoadDate": "2021-12",
    "importer": "יוניון מוטורס בע\"מ",
    "originality": "החכר",
    "colorChanged": "לא",
    "tiresChanged": "לא",
    "lpgAdded": "לא",
    "safetyScore": 1.0,
    "greenIndex": 144.0,
    "emissionGroup": 3.0,
    "f_agefuel": 0.642,
    "f_own": 0.858,
    "f_mile": 0.919,
    "f_body": 1.0,
    "f_brand": 1.06,
    "f_trim": 1.0,
    "f_safety": 0.96,
    "f_recall": 1.0,
    "f_test": 1.0,
    "f_emiss": 1.0,
    "f_orig": 1.0,
    "f_lpg": 1.0,
    "f_par": 1.0,
    "f_taxi": 1.0,
    "f_exp": 1.0,
    "factor": 0.515,
    "low": 63500.0,
    "mid": 72500.0,
    "high": 81000.0,
    "conf": 1.0,
    "yad2": 88800.0,
    "delta_yad2_pct": 0.2248275862,
    "levi": 111300.0,
    "delta_levi_pct": 0.5351724138,
    "notes": null
  },
  {
    "plate": "7368834",
    "mfg": "פיאט פולין",
    "model": "FIAT 500 1.2",
    "year": 2015.0,
    "trim": "MY LOUNGE",
    "country": "IL",
    "price_at_reg": 116900.0,
    "km": null,
    "age": 10.43,
    "ownership": "פרטי",
    "hand": 1.0,
    "hand_history": null,
    "bodyType": "הצ'בק",
    "brand_tier": "Weak-resale",
    "fuelType": "בנזין",
    "color": "שנהב לבן",
    "onRoadDate": "2015-11",
    "importer": "סמלת מוטורס בע\"מ",
    "originality": null,
    "colorChanged": null,
    "tiresChanged": null,
    "lpgAdded": null,
    "safetyScore": null,
    "greenIndex": 221.0,
    "emissionGroup": 14.0,
    "f_agefuel": 0.35,
    "f_own": 1.0,
    "f_mile": 1.0,
    "f_body": 1.0,
    "f_brand": 0.93,
    "f_trim": 1.0,
    "f_safety": 1.0,
    "f_recall": 1.0,
    "f_test": 1.0,
    "f_emiss": 1.0,
    "f_orig": 1.0,
    "f_lpg": 1.0,
    "f_par": 1.0,
    "f_taxi": 1.0,
    "f_exp": 1.0,
    "factor": 0.326,
    "low": 33000.0,
    "mid": 38000.0,
    "high": 43000.0,
    "conf": 0.85,
    "yad2": 18200.0,
    "delta_yad2_pct": -0.5210526316,
    "levi": 19000.0,
    "delta_levi_pct": -0.5,
    "notes": null
  },
  {
    "plate": "59751601",
    "mfg": "ב מ וו גרמניה",
    "model": "M850I XDRIVE",
    "year": 2019.0,
    "trim": "CARBON EDITI",
    "country": "IL",
    "price_at_reg": 1300000.0,
    "km": 156980.0,
    "age": 6.89,
    "ownership": "פרטי",
    "hand": 4.0,
    "hand_history": "החכר (03/2019) ← סוחר (06/2022) ← פרטי (09/2024) ← פרטי (09/2024)",
    "bodyType": "קופה",
    "brand_tier": "Standard",
    "fuelType": "בנזין",
    "color": "שנהב לבן",
    "onRoadDate": "2019-3",
    "importer": "דלק מוטורס בע\"מ",
    "originality": null,
    "colorChanged": "לא",
    "tiresChanged": "לא",
    "lpgAdded": "לא",
    "safetyScore": 1.0,
    "greenIndex": 350.0,
    "emissionGroup": 15.0,
    "f_agefuel": 0.509,
    "f_own": 0.808,
    "f_mile": 0.893,
    "f_body": 1.0,
    "f_brand": 1.0,
    "f_trim": 1.0,
    "f_safety": 0.96,
    "f_recall": 1.0,
    "f_test": 0.94,
    "f_emiss": 1.0,
    "f_orig": 1.0,
    "f_lpg": 1.0,
    "f_par": 1.0,
    "f_taxi": 1.0,
    "f_exp": 1.0,
    "factor": 0.331,
    "low": 379000.0,
    "mid": 430000.0,
    "high": 482000.0,
    "conf": 1.0,
    "yad2": 377600.0,
    "delta_yad2_pct": -0.1218604651,
    "levi": 313000.0,
    "delta_levi_pct": -0.2720930233,
    "notes": null
  },
  {
    "plate": "10736004",
    "mfg": "טסלה גרמניה",
    "model": "MODEL Y",
    "year": 2024.0,
    "trim": "RWD",
    "country": "IL",
    "price_at_reg": 235575.0,
    "km": 0.0,
    "age": 1.43,
    "ownership": "פרטי",
    "hand": 1.0,
    "hand_history": "פרטי (11/2024)",
    "bodyType": "פנאי-שטח",
    "brand_tier": "Standard",
    "fuelType": "חשמל",
    "color": "שנהב לבן",
    "onRoadDate": "2024-11",
    "importer": "טסלה מוטורס ישראל בע\"מ",
    "originality": null,
    "colorChanged": "לא",
    "tiresChanged": "לא",
    "lpgAdded": "לא",
    "safetyScore": 6.0,
    "greenIndex": null,
    "emissionGroup": null,
    "f_agefuel": 0.684,
    "f_own": 1.0,
    "f_mile": 1.0,
    "f_body": 1.05,
    "f_brand": 1.0,
    "f_trim": 1.0,
    "f_safety": 1.0,
    "f_recall": 1.0,
    "f_test": 0.94,
    "f_emiss": 1.0,
    "f_orig": 1.0,
    "f_lpg": 1.0,
    "f_par": 1.0,
    "f_taxi": 1.0,
    "f_exp": 1.0,
    "factor": 0.675,
    "low": 138000.0,
    "mid": 159000.0,
    "high": 179000.0,
    "conf": 0.9,
    "yad2": 188100.0,
    "delta_yad2_pct": 0.1830188679,
    "levi": 161000.0,
    "delta_levi_pct": 0.01257861635,
    "notes": null
  },
  {
    "plate": "45166601",
    "mfg": "לקסוס יפן",
    "model": "LEXUS IS300H",
    "year": 2018.0,
    "trim": "LUXURY SR",
    "country": "IL",
    "price_at_reg": 235000.0,
    "km": 168800.0,
    "age": 7.52,
    "ownership": "פרטי",
    "hand": 4.0,
    "hand_history": "פרטי (10/2018) ← סוחר (02/2022) ← פרטי (02/2022) ← פרטי (08/2025)",
    "bodyType": "סדאן",
    "brand_tier": "Premium-reliable",
    "fuelType": "בנזין",
    "color": "שנהב לבן",
    "onRoadDate": "2018-10",
    "importer": "יוניון מוטורס בע\"מ",
    "originality": null,
    "colorChanged": "לא",
    "tiresChanged": "לא",
    "lpgAdded": "לא",
    "safetyScore": 1.0,
    "greenIndex": 203.0,
    "emissionGroup": 11.0,
    "f_agefuel": 0.477,
    "f_own": 0.86,
    "f_mile": 0.888,
    "f_body": 1.0,
    "f_brand": 1.06,
    "f_trim": 1.03,
    "f_safety": 0.96,
    "f_recall": 1.0,
    "f_test": 1.0,
    "f_emiss": 1.0,
    "f_orig": 1.0,
    "f_lpg": 1.0,
    "f_par": 1.0,
    "f_taxi": 1.0,
    "f_exp": 1.0,
    "factor": 0.381,
    "low": 78500.0,
    "mid": 89500.0,
    "high": 100000.0,
    "conf": 1.0,
    "yad2": 92700.0,
    "delta_yad2_pct": 0.03575418994,
    "levi": 89760.0,
    "delta_levi_pct": 0.002905027933,
    "notes": null
  },
  {
    "plate": "33380902",
    "mfg": "סוזוקי-יפן",
    "model": "JIMNY",
    "year": 2020.0,
    "trim": "GLX",
    "country": "IL",
    "price_at_reg": 135990.0,
    "km": 42683.0,
    "age": 5.43,
    "ownership": "פרטי",
    "hand": 1.0,
    "hand_history": "פרטי (11/2020)",
    "bodyType": "פנאי-שטח",
    "brand_tier": "Standard",
    "fuelType": "בנזין",
    "color": "שנהב לבן",
    "onRoadDate": "2020-11",
    "importer": "מכשירי תנועה ומכוניות 4002 בעמ",
    "originality": null,
    "colorChanged": "לא",
    "tiresChanged": "כן",
    "lpgAdded": "לא",
    "safetyScore": 1.0,
    "greenIndex": 260.0,
    "emissionGroup": 15.0,
    "f_agefuel": 0.586,
    "f_own": 1.0,
    "f_mile": 1.078,
    "f_body": 1.05,
    "f_brand": 1.0,
    "f_trim": 1.0,
    "f_safety": 0.96,
    "f_recall": 1.0,
    "f_test": 0.94,
    "f_emiss": 1.0,
    "f_orig": 0.98,
    "f_lpg": 1.0,
    "f_par": 1.0,
    "f_taxi": 1.0,
    "f_exp": 1.0,
    "factor": 0.587,
    "low": 70000.0,
    "mid": 79500.0,
    "high": 89000.0,
    "conf": 1.0,
    "yad2": 102100.0,
    "delta_yad2_pct": 0.2842767296,
    "levi": 94000.0,
    "delta_levi_pct": 0.1823899371,
    "notes": null
  },
  {
    "plate": "33359501",
    "mfg": "מזדה יפן",
    "model": "CX-3",
    "year": 2018.0,
    "trim": "PURE WHITE",
    "country": "IL",
    "price_at_reg": 145000.0,
    "km": 43241.0,
    "age": 7.89,
    "ownership": "פרטי",
    "hand": 2.0,
    "hand_history": "פרטי (05/2018) ← פרטי (12/2024)",
    "bodyType": "פנאי-שטח",
    "brand_tier": "Standard",
    "fuelType": "בנזין",
    "color": "שנהב לבן",
    "onRoadDate": "2018-5",
    "importer": "דלק מוטורס בע\"מ",
    "originality": null,
    "colorChanged": "לא",
    "tiresChanged": "לא",
    "lpgAdded": "לא",
    "safetyScore": 2.0,
    "greenIndex": 261.0,
    "emissionGroup": 15.0,
    "f_agefuel": 0.458,
    "f_own": 0.95,
    "f_mile": 1.12,
    "f_body": 1.05,
    "f_brand": 1.0,
    "f_trim": 1.0,
    "f_safety": 0.96,
    "f_recall": 1.0,
    "f_test": 1.0,
    "f_emiss": 1.0,
    "f_orig": 1.0,
    "f_lpg": 1.0,
    "f_par": 1.0,
    "f_taxi": 1.0,
    "f_exp": 1.0,
    "factor": 0.491,
    "low": 62500.0,
    "mid": 71000.0,
    "high": 79500.0,
    "conf": 1.0,
    "yad2": 67300.0,
    "delta_yad2_pct": -0.05211267606,
    "levi": 56000.0,
    "delta_levi_pct": -0.2112676056,
    "notes": null
  },
  {
    "plate": "5520476",
    "mfg": "יונדאי צ'כיה",
    "model": "I30",
    "year": 2011.0,
    "trim": "INSPIRE",
    "country": "IL",
    "price_at_reg": 120000.0,
    "km": null,
    "age": 14.89,
    "ownership": "חברה",
    "hand": 1.0,
    "hand_history": null,
    "bodyType": "סטיישן",
    "brand_tier": "Korean-IL",
    "fuelType": "בנזין",
    "color": "שנהב לבן",
    "onRoadDate": "2011-8",
    "importer": "כלמוביל יונדאי",
    "originality": null,
    "colorChanged": null,
    "tiresChanged": null,
    "lpgAdded": null,
    "safetyScore": null,
    "greenIndex": 308.0,
    "emissionGroup": 15.0,
    "f_agefuel": 0.219,
    "f_own": 0.88,
    "f_mile": 1.0,
    "f_body": 1.0,
    "f_brand": 1.04,
    "f_trim": 1.03,
    "f_safety": 1.0,
    "f_recall": 1.0,
    "f_test": 1.0,
    "f_emiss": 1.0,
    "f_orig": 1.0,
    "f_lpg": 1.0,
    "f_par": 1.0,
    "f_taxi": 1.0,
    "f_exp": 1.0,
    "factor": 0.207,
    "low": 21500.0,
    "mid": 24500.0,
    "high": 28000.0,
    "conf": 0.85,
    "yad2": 11200.0,
    "delta_yad2_pct": -0.5428571429,
    "levi": 14000.0,
    "delta_levi_pct": -0.4285714286,
    "notes": null
  },
  {
    "plate": "78332502",
    "mfg": "יונדאי הודו",
    "model": "ACCENT",
    "year": 2022.0,
    "trim": "INSPIRE",
    "country": "IL",
    "price_at_reg": 121900.0,
    "km": 68152.0,
    "age": 3.89,
    "ownership": "פרטי",
    "hand": 2.0,
    "hand_history": "החכר (03/2022) ← פרטי (04/2025)",
    "bodyType": "סדאן",
    "brand_tier": "Korean-IL",
    "fuelType": "בנזין",
    "color": "כסף",
    "onRoadDate": "2022-3",
    "importer": "כלמוביל יונדאי",
    "originality": "החכר",
    "colorChanged": "לא",
    "tiresChanged": "לא",
    "lpgAdded": "לא",
    "safetyScore": null,
    "greenIndex": 266.0,
    "emissionGroup": 15.0,
    "f_agefuel": 0.667,
    "f_own": 0.858,
    "f_mile": 0.98,
    "f_body": 1.0,
    "f_brand": 1.04,
    "f_trim": 1.03,
    "f_safety": 1.0,
    "f_recall": 1.0,
    "f_test": 1.0,
    "f_emiss": 1.0,
    "f_orig": 1.0,
    "f_lpg": 1.0,
    "f_par": 1.0,
    "f_taxi": 1.0,
    "f_exp": 1.0,
    "factor": 0.601,
    "low": 64000.0,
    "mid": 73000.0,
    "high": 82000.0,
    "conf": 1.0,
    "yad2": 62200.0,
    "delta_yad2_pct": -0.1479452055,
    "levi": 71400.0,
    "delta_levi_pct": -0.02191780822,
    "notes": null
  },
  {
    "plate": "75033502",
    "mfg": "סיטרואן ספרד",
    "model": "BERLINGO",
    "year": 2022.0,
    "trim": "SHINE PK N1",
    "country": "IL",
    "price_at_reg": 149990.0,
    "km": null,
    "age": 3.89,
    "ownership": "פרטי",
    "hand": 1.0,
    "hand_history": null,
    "bodyType": "סגור/משלוח",
    "brand_tier": "Weak-resale",
    "fuelType": "דיזל",
    "color": "שנהב לבן",
    "onRoadDate": "2022-2",
    "importer": "דוד לובינסקי בע\"מ",
    "originality": null,
    "colorChanged": null,
    "tiresChanged": null,
    "lpgAdded": null,
    "safetyScore": null,
    "greenIndex": 256.0,
    "emissionGroup": 15.0,
    "f_agefuel": 0.653,
    "f_own": 1.0,
    "f_mile": 1.0,
    "f_body": 1.0,
    "f_brand": 0.93,
    "f_trim": 1.0,
    "f_safety": 1.0,
    "f_recall": 1.0,
    "f_test": 1.0,
    "f_emiss": 1.0,
    "f_orig": 1.0,
    "f_lpg": 1.0,
    "f_par": 1.0,
    "f_taxi": 1.0,
    "f_exp": 1.0,
    "factor": 0.608,
    "low": 79000.0,
    "mid": 91000.0,
    "high": 103000.0,
    "conf": 0.85,
    "yad2": 81200.0,
    "delta_yad2_pct": -0.1076923077,
    "levi": 94200.0,
    "delta_levi_pct": 0.03516483516,
    "notes": null
  },
  {
    "plate": "3980775",
    "mfg": "מזדה יפן",
    "model": "MAZDA 3",
    "year": 2011.0,
    "trim": "ACTIVE",
    "country": "IL",
    "price_at_reg": 120000.0,
    "km": null,
    "age": 14.35,
    "ownership": "פרטי",
    "hand": 1.0,
    "hand_history": null,
    "bodyType": "סדאן",
    "brand_tier": "Standard",
    "fuelType": "בנזין",
    "color": "כסף",
    "onRoadDate": "2011-12",
    "importer": "דלק מוטורס בע\"מ",
    "originality": null,
    "colorChanged": null,
    "tiresChanged": null,
    "lpgAdded": null,
    "safetyScore": null,
    "greenIndex": 309.0,
    "emissionGroup": 15.0,
    "f_agefuel": 0.232,
    "f_own": 1.0,
    "f_mile": 1.0,
    "f_body": 1.0,
    "f_brand": 1.0,
    "f_trim": 1.0,
    "f_safety": 1.0,
    "f_recall": 1.0,
    "f_test": 1.0,
    "f_emiss": 1.0,
    "f_orig": 1.0,
    "f_lpg": 1.0,
    "f_par": 1.0,
    "f_taxi": 1.0,
    "f_exp": 1.0,
    "factor": 0.232,
    "low": 24000.0,
    "mid": 27500.0,
    "high": 31500.0,
    "conf": 0.85,
    "yad2": 12900.0,
    "delta_yad2_pct": -0.5309090909,
    "levi": 13700.0,
    "delta_levi_pct": -0.5018181818,
    "notes": null
  },
  {
    "plate": "78714903",
    "mfg": "יונדאי קוריאה",
    "model": "ELANTRA HEV",
    "year": 2024.0,
    "trim": "PREMIUM FL",
    "country": "IL",
    "price_at_reg": 169900.0,
    "km": 0.0,
    "age": 1.89,
    "ownership": "ליסינג",
    "hand": 1.0,
    "hand_history": "החכר (06/2024)",
    "bodyType": "סדאן",
    "brand_tier": "Korean-IL",
    "fuelType": "בנזין",
    "color": "שנהב לבן",
    "onRoadDate": "2024-6",
    "importer": "כלמוביל יונדאי",
    "originality": "החכר",
    "colorChanged": "לא",
    "tiresChanged": "לא",
    "lpgAdded": "לא",
    "safetyScore": 4.0,
    "greenIndex": 154.0,
    "emissionGroup": 4.0,
    "f_agefuel": 0.778,
    "f_own": 0.82,
    "f_mile": 1.0,
    "f_body": 1.0,
    "f_brand": 1.04,
    "f_trim": 1.03,
    "f_safety": 1.0,
    "f_recall": 1.0,
    "f_test": 1.0,
    "f_emiss": 1.0,
    "f_orig": 1.0,
    "f_lpg": 1.0,
    "f_par": 1.0,
    "f_taxi": 1.0,
    "f_exp": 1.0,
    "factor": 0.684,
    "low": 101000.0,
    "mid": 116000.0,
    "high": 131000.0,
    "conf": 0.9,
    "yad2": 139200.0,
    "delta_yad2_pct": 0.2,
    "levi": 145500.0,
    "delta_levi_pct": 0.2543103448,
    "notes": null
  }
]